presidio_analyzer/__init__.py
presidio_analyzer/analysis_explanation.py
presidio_analyzer/analyzer_engine.py
presidio_analyzer/app.py
presidio_analyzer/app_tracer.py
presidio_analyzer/entity_recognizer.py
presidio_analyzer/local_recognizer.py
presidio_analyzer/pattern.py
presidio_analyzer/pattern_recognizer.py
presidio_analyzer/presidio-analyzer
presidio_analyzer/presidio-analyzer.bat
presidio_analyzer/presidio_logger.py
presidio_analyzer/recognizer_result.py
presidio_analyzer/remote_recognizer.py
presidio_analyzer/nlp_engine/__init__.py
presidio_analyzer/nlp_engine/nlp_artifacts.py
presidio_analyzer/nlp_engine/nlp_engine.py
presidio_analyzer/nlp_engine/spacy_nlp_engine.py
presidio_analyzer/nlp_engine/stanza_nlp_engine.py
presidio_analyzer/predefined_recognizers/__init__.py
presidio_analyzer/predefined_recognizers/aba_routing_recognizer.py
presidio_analyzer/predefined_recognizers/credit_card_recognizer.py
presidio_analyzer/predefined_recognizers/crypto_recognizer.py
presidio_analyzer/predefined_recognizers/domain_recognizer.py
presidio_analyzer/predefined_recognizers/email_recognizer.py
presidio_analyzer/predefined_recognizers/iban_patterns.py
presidio_analyzer/predefined_recognizers/iban_recognizer.py
presidio_analyzer/predefined_recognizers/ip_recognizer.py
presidio_analyzer/predefined_recognizers/sg_fin_recognizer.py
presidio_analyzer/predefined_recognizers/spacy_recognizer.py
presidio_analyzer/predefined_recognizers/stanza_recognizer.py
presidio_analyzer/predefined_recognizers/uk_nhs_recognizer.py
presidio_analyzer/predefined_recognizers/us_bank_recognizer.py
presidio_analyzer/predefined_recognizers/us_driver_license_recognizer.py
presidio_analyzer/predefined_recognizers/us_itin_recognizer.py
presidio_analyzer/predefined_recognizers/us_passport_recognizer.py
presidio_analyzer/predefined_recognizers/us_phone_recognizer.py
presidio_analyzer/predefined_recognizers/us_ssn_recognizer.py
presidio_analyzer/protobuf_models/__init__.py
presidio_analyzer_fixed-0.5.dev0.dist-info/METADATA
presidio_analyzer_fixed-0.5.dev0.dist-info/WHEEL
presidio_analyzer_fixed-0.5.dev0.dist-info/top_level.txt
presidio_analyzer_fixed-0.5.dev0.dist-info/RECORD
