Metadata-Version: 2.1
Name: presidio-analyzer-fixed
Version: 0.5.dev0
Summary: Presidio analyzer package
Home-page: https://github.com/Microsoft/presidio
Author: UNKNOWN
Author-email: UNKNOWN
License: MIT
Platform: UNKNOWN
Classifier: Programming Language :: Python :: 3
Classifier: License :: OSI Approved :: MIT License
Classifier: Operating System :: OS Independent
Requires-Dist: cython (==0.29.10)
Requires-Dist: spacy (==2.2.3)
Requires-Dist: regex (==2019.6.8)
Requires-Dist: grpcio (==1.31.0)
Requires-Dist: protobuf (==3.8.0)
Requires-Dist: tldextract (==2.2.1)
Requires-Dist: knack (==0.6.2)
